README.rst
setup.cfg
setup.py
rpki_rtr_client.egg-info/PKG-INFO
rpki_rtr_client.egg-info/SOURCES.txt
rpki_rtr_client.egg-info/dependency_links.txt
rpki_rtr_client.egg-info/entry_points.txt
rpki_rtr_client.egg-info/requires.txt
rpki_rtr_client.egg-info/top_level.txt
rtr_client/__init__.py
rtr_client/rtr_client.py
rtr_client/rtr_file_process.py
rtr_client/rtr_logging.py
rtr_client/rtr_protocol.py
rtr_client/rtr_routes.py
rtr_client/rtr_show.py
rtr_client/rtr_ssh.py