Metadata-Version: 1.1
Name: rpki-rtr-client
Version: 1.0.5
Summary: A simple client-side implementation of the RTR RFC8210 protocol in Python
Home-page: https://github.com/cloudflare/rpki-rtr-client
Author: Martin J. Levy
Author-email: martin@cloudflare.com
License: BSD 3
Keywords: RFC9210,RPKI,RTR,Cloudflare
Platform: UNKNOWN
Classifier: Development Status :: 5 - Production/Stable
Classifier: Intended Audience :: Developers
Classifier: Topic :: Software Development :: Libraries :: Python Modules
Classifier: License :: OSI Approved :: MIT License
Classifier: Programming Language :: Python :: 3
